ChemInterface_ppchem/ChemInterface.py
ChemInterface_ppchem/__init__.py
cheminterface_ppchem-2.2.dist-info/METADATA
cheminterface_ppchem-2.2.dist-info/WHEEL
cheminterface_ppchem-2.2.dist-info/licenses/LICENSE.txt
cheminterface_ppchem-2.2.dist-info/RECORD
