Metadata-Version: 2.3
Name: ChemInterface_ppchem
Version: 2.2
Summary: ...
Project-URL: Homepage, https://github.com/ThomasCsson/ppchem-project-Christiansson-Gonteri-Humery.git
Author-email: Thomas Christianson <thomas.christiansson@epfl.ch>, Igor Gonteri <igor.gonteri@epfl.ch>, Arthur Humery <arthur.humery@epfl.ch>
License-Expression: MIT
License-File: LICENSE.txt
Keywords: Mass spectroscopy,unsaturation
Classifier: Development Status :: 4 - Beta
Classifier: License :: OSI Approved :: MIT License
Classifier: Operating System :: OS Independent
Classifier: Programming Language :: Python :: 3
Requires-Python: >=3.8
Requires-Dist: bokeh
Requires-Dist: matplotlib
Requires-Dist: numpy
Requires-Dist: pandas
Requires-Dist: plotly
Requires-Dist: rdkit
